.travis.yml
MANIFEST.in
README.rst
setup.py
tox.ini
mr/__init__.py
mr.awsome.virtualbox.egg-info/PKG-INFO
mr.awsome.virtualbox.egg-info/SOURCES.txt
mr.awsome.virtualbox.egg-info/dependency_links.txt
mr.awsome.virtualbox.egg-info/entry_points.txt
mr.awsome.virtualbox.egg-info/namespace_packages.txt
mr.awsome.virtualbox.egg-info/not-zip-safe
mr.awsome.virtualbox.egg-info/requires.txt
mr.awsome.virtualbox.egg-info/top_level.txt
mr/awsome_virtualbox/__init__.py
mr/awsome_virtualbox/test_virtualbox.py
mr/awsome_virtualbox/vbox.py
mr/awsome_virtualbox/vboxmanage.txt