Metadata-Version: 1.0
Name: mr.awsome.virtualbox
Version: 1.0b1
Summary: A plugin for mr.awsome providing support for VMs using VirtualBox.
Home-page: http://github.com/fschulze/mr.awsome.virtualbox
Author: Florian Schulze
Author-email: florian.schulze@gmx.net
License: UNKNOWN
Platform: UNKNOWN
